[
  {
    "tipo": "depoimento",
    "titulo": "Salvaram Meu Gato às 23h!",
    "corpo": "💙 Depoimento da Dona Maria:\n\n\"Meu gato Thor estava com febre alta às 23h. \nLiguei desesperada e em 40 minutos:\n✅ Entregaram o antibiótico\n✅ Veterinário orientou pelo WhatsApp\n✅ Hoje o Thor está CURADO!\"\n\n🌙 Emergência? Estamos aqui 24/7!\n📱 WhatsApp: 31999887766",
    "cta_button": {
      "tipo": "WHATSAPP",
      "texto": "Estamos aqui 24/7!",
      "link": "https://wa.me/5531999887766"
    },
    "palavras_chave": [
      "emergência",
      "depoimento",
      "24h"
    ],
    "emoji_destaque": "😊",
    "melhor_horario": "18:00",
    "data_sugerida": "2026-02-06 11:53:31.975165",
    "data_publicacao": "2026-02-06 18:00"
  },
  {
    "tipo": "dica_saude",
    "titulo": "Vermifugação em Dia Salva Vidas",
    "corpo": "🐾 Seu pet tomou vermífugo nos últimos 3 meses?\n\nParasitas invisíveis podem causar:\n• Anemia grave\n• Perda de peso\n• Vômitos e diarreia\n• Problemas intestinais\n\n📍 Temos todas as marcas em estoque\n💬 Dúvidas? Nosso veterinário responde AGORA!",
    "cta_button": {
      "tipo": "CALL",
      "texto": "Tire suas dúvidas!",
      "link": "tel:+5531999887766"
    },
    "palavras_chave": [
      "vermífugo",
      "parasitas",
      "prevenção"
    ],
    "emoji_destaque": "🏥",
    "melhor_horario": "09:00",
    "data_sugerida": "2026-02-09 11:53:31.974869",
    "data_publicacao": "2026-02-09 09:00"
  },
  {
    "tipo": "vet_casa",
    "titulo": "Veterinário no Conforto do Seu Lar",
    "corpo": "🏠 Chega de estresse com transporte e salas de espera barulhentas!\n\nLevamos a clínica veterinária até você:\n✅ Consultas completas\n✅ Vacinação importada\n✅ Coleta de exames\n✅ Tudo no ambiente que seu pet ama\n\n📍 Atendemos BH e Região Metropolitana.\n💬 Agende agora pelo WhatsApp!",
    "cta_button": {
      "tipo": "WHATSAPP",
      "texto": "Agende pelo Whats!",
      "link": "https://wa.me/5531999887766?text=Olá!%20Vim%20pelo%20Google%20e%20quero%20saber%20mais%20sobre%20o%20Vet%20em%20Casa."
    },
    "palavras_chave": [
      "vet em casa",
      "atendimento domiciliar",
      "bh"
    ],
    "emoji_destaque": "🏠",
    "melhor_horario": "10:00",
    "data_sugerida": "2026-02-10 11:53:31.975303",
    "data_publicacao": "2026-02-10 10:00"
  },
  {
    "tipo": "produto_destaque",
    "titulo": "20% OFF: Royal Canin Gastro Intestinal",
    "corpo": "🔥 OFERTA DA SEMANA!\n\nRoyal Canin Gastro Intestinal\nDE: R$ 350.00\nPOR: R$ 280.00\n💰 Economia: 20%!\n\n✅ Entrega GRÁTIS em BH\n✅ Parcelamos em 3x sem juros\n✅ Produto certificado\n\n⏰ Válido até sexta-feira!\n📱 Peça pelo WhatsApp: 31999887766",
    "cta_button": {
      "tipo": "WHATSAPP",
      "texto": "Quero aproveitar!",
      "link": "https://wa.me/5531999887766?text=Oi!%20Quero%20a%20oferta%20de%20Royal Canin Gastro Intestinal"
    },
    "palavras_chave": [
      "Royal Canin Gastro Intestinal",
      "oferta",
      "ração"
    ],
    "emoji_destaque": "🔥",
    "melhor_horario": "14:00",
    "data_sugerida": "2026-02-11 11:53:31.975008",
    "produto": {
      "nome": "Royal Canin Gastro Intestinal",
      "preco_de": 350,
      "preco_por": 280,
      "categoria": "ração"
    },
    "data_publicacao": "2026-02-11 14:00"
  },
  {
    "tipo": "depoimento",
    "titulo": "Veterinária Confia na Otimiza",
    "corpo": "🩺 Dra. Ana Paula, veterinária há 15 anos:\n\n\"Indico a Otimiza para TODOS os meus clientes porque:\n✓ Produtos certificados\n✓ Entrega rápida\n✓ Preços justos\n✓ Equipe que entende do assunto\"\n\n👩‍⚕️ Profissionais confiam. Você também pode!\n📍 Visite nossa loja em BH",
    "cta_button": {
      "tipo": "WHATSAPP",
      "texto": "Conte conosco!",
      "link": "https://wa.me/5531999887766"
    },
    "palavras_chave": [
      "veterinário",
      "confiança",
      "profissional"
    ],
    "emoji_destaque": "🙏",
    "melhor_horario": "18:00",
    "data_sugerida": "2026-02-06 11:53:31.975200",
    "data_publicacao": "2026-02-13 18:00"
  },
  {
    "tipo": "dica_saude",
    "titulo": "Vermifugação em Dia Salva Vidas",
    "corpo": "🐾 Seu pet tomou vermífugo nos últimos 3 meses?\n\nParasitas invisíveis podem causar:\n• Anemia grave\n• Perda de peso\n• Vômitos e diarreia\n• Problemas intestinais\n\n📍 Temos todas as marcas em estoque\n💬 Dúvidas? Nosso veterinário responde AGORA!",
    "cta_button": {
      "tipo": "CALL",
      "texto": "Dúvidas? WhatsApp!",
      "link": "tel:+5531999887766"
    },
    "palavras_chave": [
      "vermífugo",
      "parasitas",
      "prevenção"
    ],
    "emoji_destaque": "⚕️",
    "melhor_horario": "09:00",
    "data_sugerida": "2026-02-09 11:53:31.974923",
    "data_publicacao": "2026-02-16 09:00"
  },
  {
    "tipo": "vet_casa",
    "titulo": "Comportamento Canino: Especialista em Casa",
    "corpo": "🐕 Problemas de comportamento? Nós ajudamos!\n\n✨ Mais de 1.000 atendimentos desde 2012.\nAvaliação completa de:\n• Ansiedade e Medos\n• Agressividade\n• Destruição de objetos\n• Adaptação de novos pets\n\n🏠 No ambiente real onde os problemas acontecem.\n💬 Saiba mais pelo WhatsApp!",
    "cta_button": {
      "tipo": "WHATSAPP",
      "texto": "Agende pelo Whats!",
      "link": "https://wa.me/5531999887766?text=Olá!%20Vim%20pelo%20Google%20e%20quero%20saber%20mais%20sobre%20o%20Vet%20em%20Casa."
    },
    "palavras_chave": [
      "comportamento canino",
      "adestramento",
      "psicologia animal"
    ],
    "emoji_destaque": "🩺",
    "melhor_horario": "10:00",
    "data_sugerida": "2026-02-10 11:53:31.975334",
    "data_publicacao": "2026-02-17 10:00"
  },
  {
    "tipo": "produto_destaque",
    "titulo": "15% OFF: Bravecto 20-40kg",
    "corpo": "🔥 OFERTA DA SEMANA!\n\nBravecto 20-40kg\nDE: R$ 195.00\nPOR: R$ 165.00\n💰 Economia: 15%!\n\n✅ Entrega GRÁTIS em BH\n✅ Parcelamos em 3x sem juros\n✅ Produto certificado\n\n⏰ Válido até sexta-feira!\n📱 Peça pelo WhatsApp: 31999887766",
    "cta_button": {
      "tipo": "WHATSAPP",
      "texto": "Quero aproveitar!",
      "link": "https://wa.me/5531999887766?text=Oi!%20Quero%20a%20oferta%20de%20Bravecto 20-40kg"
    },
    "palavras_chave": [
      "Bravecto 20-40kg",
      "oferta",
      "antipulgas"
    ],
    "emoji_destaque": "🔥",
    "melhor_horario": "14:00",
    "data_sugerida": "2026-02-11 11:53:31.975046",
    "produto": {
      "nome": "Bravecto 20-40kg",
      "preco_de": 195,
      "preco_por": 165,
      "categoria": "antipulgas"
    },
    "data_publicacao": "2026-02-18 14:00"
  },
  {
    "tipo": "depoimento",
    "titulo": "Veterinária Confia na Otimiza",
    "corpo": "🩺 Dra. Ana Paula, veterinária há 15 anos:\n\n\"Indico a Otimiza para TODOS os meus clientes porque:\n✓ Produtos certificados\n✓ Entrega rápida\n✓ Preços justos\n✓ Equipe que entende do assunto\"\n\n👩‍⚕️ Profissionais confiam. Você também pode!\n📍 Visite nossa loja em BH",
    "cta_button": {
      "tipo": "WHATSAPP",
      "texto": "Você também pode confiar!",
      "link": "https://wa.me/5531999887766"
    },
    "palavras_chave": [
      "veterinário",
      "confiança",
      "profissional"
    ],
    "emoji_destaque": "😊",
    "melhor_horario": "18:00",
    "data_sugerida": "2026-02-06 11:53:31.975234",
    "data_publicacao": "2026-02-20 18:00"
  },
  {
    "tipo": "dica_saude",
    "titulo": "Antipulgas: Quando Aplicar?",
    "corpo": "🔍 Seu cachorro está coçando muito?\n\nPulgas se reproduzem RÁPIDO:\n• 1 pulga = 50 ovos por dia\n• Em 3 semanas = infestação total\n• Causam alergias e anemia\n\n✅ Aplicação mensal é ESSENCIAL\n📦 Temos: Bravecto, Simparic, NexGard\n\n💬 WhatsApp: Qual o melhor para seu pet?",
    "cta_button": {
      "tipo": "CALL",
      "texto": "Fale com nosso vet!",
      "link": "tel:+5531999887766"
    },
    "palavras_chave": [
      "antipulgas",
      "bravecto",
      "simparic"
    ],
    "emoji_destaque": "⚕️",
    "melhor_horario": "09:00",
    "data_sugerida": "2026-02-09 11:53:31.974954",
    "data_publicacao": "2026-02-23 09:00"
  },
  {
    "tipo": "vet_casa",
    "titulo": "Comportamento Canino: Especialista em Casa",
    "corpo": "🐕 Problemas de comportamento? Nós ajudamos!\n\n✨ Mais de 1.000 atendimentos desde 2012.\nAvaliação completa de:\n• Ansiedade e Medos\n• Agressividade\n• Destruição de objetos\n• Adaptação de novos pets\n\n🏠 No ambiente real onde os problemas acontecem.\n💬 Saiba mais pelo WhatsApp!",
    "cta_button": {
      "tipo": "WHATSAPP",
      "texto": "Chamar Vet em Casa!",
      "link": "https://wa.me/5531999887766?text=Olá!%20Vim%20pelo%20Google%20e%20quero%20saber%20mais%20sobre%20o%20Vet%20em%20Casa."
    },
    "palavras_chave": [
      "comportamento canino",
      "adestramento",
      "psicologia animal"
    ],
    "emoji_destaque": "🐱",
    "melhor_horario": "10:00",
    "data_sugerida": "2026-02-10 11:53:31.975380",
    "data_publicacao": "2026-02-24 10:00"
  },
  {
    "tipo": "produto_destaque",
    "titulo": "20% OFF: Simparic 40mg",
    "corpo": "🔥 OFERTA DA SEMANA!\n\nSimparic 40mg\nDE: R$ 120.00\nPOR: R$ 95.00\n💰 Economia: 20%!\n\n✅ Entrega GRÁTIS em BH\n✅ Parcelamos em 3x sem juros\n✅ Produto certificado\n\n⏰ Válido até sexta-feira!\n📱 Peça pelo WhatsApp: 31999887766",
    "cta_button": {
      "tipo": "WHATSAPP",
      "texto": "Quero aproveitar!",
      "link": "https://wa.me/5531999887766?text=Oi!%20Quero%20a%20oferta%20de%20Simparic 40mg"
    },
    "palavras_chave": [
      "Simparic 40mg",
      "oferta",
      "antipulgas"
    ],
    "emoji_destaque": "🔥",
    "melhor_horario": "14:00",
    "data_sugerida": "2026-02-11 11:53:31.975090",
    "produto": {
      "nome": "Simparic 40mg",
      "preco_de": 120,
      "preco_por": 95,
      "categoria": "antipulgas"
    },
    "data_publicacao": "2026-02-25 14:00"
  },
  {
    "tipo": "depoimento",
    "titulo": "Salvaram Meu Gato às 23h!",
    "corpo": "💙 Depoimento da Dona Maria:\n\n\"Meu gato Thor estava com febre alta às 23h. \nLiguei desesperada e em 40 minutos:\n✅ Entregaram o antibiótico\n✅ Veterinário orientou pelo WhatsApp\n✅ Hoje o Thor está CURADO!\"\n\n🌙 Emergência? Estamos aqui 24/7!\n📱 WhatsApp: 31999887766",
    "cta_button": {
      "tipo": "WHATSAPP",
      "texto": "Conte conosco!",
      "link": "https://wa.me/5531999887766"
    },
    "palavras_chave": [
      "emergência",
      "depoimento",
      "24h"
    ],
    "emoji_destaque": "😊",
    "melhor_horario": "18:00",
    "data_sugerida": "2026-02-06 11:53:31.975261",
    "data_publicacao": "2026-02-27 18:00"
  }
]